image_toolbox/__init__.py
image_toolbox/__main__.py
cli_image_toolbox-0.1.1.dist-info/METADATA
cli_image_toolbox-0.1.1.dist-info/WHEEL
cli_image_toolbox-0.1.1.dist-info/entry_points.txt
cli_image_toolbox-0.1.1.dist-info/licenses/LICENSE
cli_image_toolbox-0.1.1.dist-info/RECORD
