Metadata-Version: 2.1
Name: cli-image-toolbox
Version: 0.1.1
Summary: CLI tool for renaming images with a specified format.
Project-URL: Homepage, https://codeberg.org/wime/tool-image-toolbox
Author-email: Willem Meijer <willem.meijer@mailbox.org>
License-File: LICENSE
Keywords: cli,images,script
Requires-Python: >=3.10
Requires-Dist: pillow>=10.0.1
